README.rst
setup.py
clodoo/LICENSE
clodoo/__init__.py
clodoo/__main__.py
clodoo/bck_filestore.sh
clodoo/clodoo_main.py
clodoo/clodoocore.py
clodoo/clodoolib.py
clodoo/cron_cscs.py
clodoo/force_password.sh
clodoo/install_wkhtmltopdf.0.12.4.sh
clodoo/odoo12_notes.txt
clodoo/odoo_skin.sh
clodoo/odoorc
clodoo/transodoo.py
clodoo/transodoo.xlsx
clodoo/update_coa.py
clodoo.egg-info/PKG-INFO
clodoo.egg-info/SOURCES.txt
clodoo.egg-info/dependency_links.txt
clodoo.egg-info/entry_points.txt
clodoo.egg-info/not-zip-safe
clodoo.egg-info/requires.txt
clodoo.egg-info/top_level.txt
clodoo/data/account-journal.csv
clodoo/data/account_fiscalyear-cur-31.csv
clodoo/data/account_fiscalyear-prior-31.csv
clodoo/data/account_invoice-61-1.csv
clodoo/data/account_invoice-61-2.csv
clodoo/data/account_invoice-61-3.csv
clodoo/data/account_invoice_line-61-1.csv
clodoo/data/account_invoice_line-61-2.csv
clodoo/data/account_invoice_line-61-3.csv
clodoo/data/account_journal-15.csv
clodoo/data/account_journal-16.csv
clodoo/data/account_journal-16_6.1.csv
clodoo/data/account_journal-main-90.csv
clodoo/data/account_journal-main-91.csv
clodoo/data/account_move-62-1.csv
clodoo/data/account_move_line-62-1.csv
clodoo/data/account_period-cur-31.csv
clodoo/data/account_period-prior-31.csv
clodoo/data/account_tax_code-20.csv
clodoo/data/crm_lead-54.csv
clodoo/data/ir_config_parameter-03.csv
clodoo/data/ir_config_parameter-13.csv
clodoo/data/ir_config_parameter-13_10.0.csv
clodoo/data/ir_config_parameter-13_8.0.csv
clodoo/data/ir_mail_server-13.csv
clodoo/data/ir_rule-13_7.0.csv
clodoo/data/ir_sequence-15.csv
clodoo/data/ir_sequence-16.csv
clodoo/data/payment-mode.csv
clodoo/data/product_product-demo-55.csv
clodoo/data/product_product-demo-55_6.1.csv
clodoo/data/res-partners.csv
clodoo/data/res_bank-22.csv
clodoo/data/res_company-demo-52.csv
clodoo/data/res_company-main-12.csv
clodoo/data/res_company-new-12.csv
clodoo/data/res_country-2.csv
clodoo/data/res_group-all-14.csv
clodoo/data/res_group-all-21.csv
clodoo/data/res_group-demo-51.csv
clodoo/data/res_group-main-11.csv
clodoo/data/res_group-main-11_6.1.csv
clodoo/data/res_group-new-12.csv
clodoo/data/res_group-new-12_6.1.csv
clodoo/data/res_lang.csv
clodoo/egg-info/CHANGELOG.rst
clodoo/egg-info/CONTRIBUTORS.txt
clodoo/egg-info/DESCRIPTION.rst
clodoo/egg-info/FEATURES.csv
clodoo/egg-info/FEATURES.rst
clodoo/egg-info/__manifest__.rst
clodoo/egg-info/description_features.csv
clodoo/egg-info/description_transodoo.rst
